<?xml version="1.0" encoding="utf-8"?>
<Patch>
  <!-- Speed -->
  <Operation Class="PatchOperationConditional">
    <xpath>*/StatDef[defName = "MiningSpeed"]/parts</xpath>
    <match Class="PatchOperationAdd">
      <xpath>*/StatDef[defName = "MiningSpeed"]/parts</xpath>
        <order>Prepend</order>
        <value>
          <li Class="Maux36.RimPsyche.Disposition.PsycheDeliberationWorkspeedStatPart"/>
        </value>
    </match>
    <nomatch Class="PatchOperationAdd">
      <xpath>*/StatDef[defName = "MiningSpeed"]</xpath>
        <order>Prepend</order>
        <value>
          <parts>
            <li Class="Maux36.RimPsyche.Disposition.PsycheDeliberationWorkspeedStatPart"/>
          </parts>
        </value>
    </nomatch>
  </Operation>
  
  <Operation Class="PatchOperationConditional">
    <xpath>*/StatDef[defName = "DeepDrillingSpeed"]/parts</xpath>
    <match Class="PatchOperationAdd">
      <xpath>*/StatDef[defName = "DeepDrillingSpeed"]/parts</xpath>
        <order>Prepend</order>
        <value>
          <li Class="Maux36.RimPsyche.Disposition.PsycheDeliberationWorkspeedStatPart"/>
        </value>
    </match>
    <nomatch Class="PatchOperationAdd">
      <xpath>*/StatDef[defName = "DeepDrillingSpeed"]</xpath>
        <order>Prepend</order>
        <value>
          <parts>
            <li Class="Maux36.RimPsyche.Disposition.PsycheDeliberationWorkspeedStatPart"/>
          </parts>
        </value>
    </nomatch>
  </Operation>

  <Operation Class="PatchOperationConditional">
    <xpath>*/StatDef[defName = "AnimalGatherSpeed"]/parts</xpath>
    <match Class="PatchOperationAdd">
      <xpath>*/StatDef[defName = "AnimalGatherSpeed"]/parts</xpath>
        <order>Prepend</order>
        <value>
          <li Class="Maux36.RimPsyche.Disposition.PsycheDeliberationWorkspeedStatPart"/>
        </value>
    </match>
    <nomatch Class="PatchOperationAdd">
      <xpath>*/StatDef[defName = "AnimalGatherSpeed"]</xpath>
        <order>Prepend</order>
        <value>
          <parts>
            <li Class="Maux36.RimPsyche.Disposition.PsycheDeliberationWorkspeedStatPart"/>
          </parts>
        </value>
    </nomatch>
  </Operation>

  <Operation Class="PatchOperationConditional">
    <xpath>*/StatDef[defName = "PlantWorkSpeed"]/parts</xpath>
    <match Class="PatchOperationAdd">
      <xpath>*/StatDef[defName = "PlantWorkSpeed"]/parts</xpath>
        <order>Prepend</order>
        <value>
          <li Class="Maux36.RimPsyche.Disposition.PsycheDeliberationWorkspeedStatPart"/>
        </value>
    </match>
    <nomatch Class="PatchOperationAdd">
      <xpath>*/StatDef[defName = "PlantWorkSpeed"]</xpath>
        <order>Prepend</order>
        <value>
          <parts>
            <li Class="Maux36.RimPsyche.Disposition.PsycheDeliberationWorkspeedStatPart"/>
          </parts>
        </value>
    </nomatch>
  </Operation>

  <Operation Class="PatchOperationConditional">
    <xpath>*/StatDef[defName = "ConstructionSpeed"]/parts</xpath>
    <match Class="PatchOperationAdd">
      <xpath>*/StatDef[defName = "ConstructionSpeed"]/parts</xpath>
        <order>Prepend</order>
        <value>
          <li Class="Maux36.RimPsyche.Disposition.PsycheDeliberationWorkspeedStatPart"/>
        </value>
    </match>
    <nomatch Class="PatchOperationAdd">
      <xpath>*/StatDef[defName = "ConstructionSpeed"]</xpath>
        <order>Prepend</order>
        <value>
          <parts>
            <li Class="Maux36.RimPsyche.Disposition.PsycheDeliberationWorkspeedStatPart"/>
          </parts>
        </value>
    </nomatch>
  </Operation>

  <Operation Class="PatchOperationConditional">
    <xpath>*/StatDef[defName = "MedicalTendSpeed"]/parts</xpath>
    <match Class="PatchOperationAdd">
      <xpath>*/StatDef[defName = "MedicalTendSpeed"]/parts</xpath>
        <order>Prepend</order>
        <value>
          <li Class="Maux36.RimPsyche.Disposition.PsycheDeliberationWorkspeedStatPart"/>
        </value>
    </match>
    <nomatch Class="PatchOperationAdd">
      <xpath>*/StatDef[defName = "MedicalTendSpeed"]</xpath>
        <order>Prepend</order>
        <value>
          <parts>
            <li Class="Maux36.RimPsyche.Disposition.PsycheDeliberationWorkspeedStatPart"/>
          </parts>
        </value>
    </nomatch>
  </Operation>

  <Operation Class="PatchOperationConditional">
    <xpath>*/StatDef[defName = "MedicalOperationSpeed"]/parts</xpath>
    <match Class="PatchOperationAdd">
      <xpath>*/StatDef[defName = "MedicalOperationSpeed"]/parts</xpath>
        <order>Prepend</order>
        <value>
          <li Class="Maux36.RimPsyche.Disposition.PsycheDeliberationWorkspeedStatPart"/>
        </value>
    </match>
    <nomatch Class="PatchOperationAdd">
      <xpath>*/StatDef[defName = "MedicalOperationSpeed"]</xpath>
        <order>Prepend</order>
        <value>
          <parts>
            <li Class="Maux36.RimPsyche.Disposition.PsycheDeliberationWorkspeedStatPart"/>
          </parts>
        </value>
    </nomatch>
  </Operation>

  <Operation Class="PatchOperationConditional">
    <xpath>*/StatDef[defName = "CookSpeed"]/parts</xpath>
    <match Class="PatchOperationAdd">
      <xpath>*/StatDef[defName = "CookSpeed"]/parts</xpath>
        <order>Prepend</order>
        <value>
          <li Class="Maux36.RimPsyche.Disposition.PsycheDeliberationCookingSpeedStatPart"/>
        </value>
    </match>
    <nomatch Class="PatchOperationAdd">
      <xpath>*/StatDef[defName = "CookSpeed"]</xpath>
        <order>Prepend</order>
        <value>
          <parts>
            <li Class="Maux36.RimPsyche.Disposition.PsycheDeliberationCookingSpeedStatPart"/>
          </parts>
        </value>
    </nomatch>
  </Operation>

  <Operation Class="PatchOperationConditional">
    <xpath>*/StatDef[defName = "ButcheryFleshSpeed"]/parts</xpath>
    <match Class="PatchOperationAdd">
      <xpath>*/StatDef[defName = "ButcheryFleshSpeed"]/parts</xpath>
        <order>Prepend</order>
        <value>
          <li Class="Maux36.RimPsyche.Disposition.PsycheDeliberationWorkspeedStatPart"/>
        </value>
    </match>
    <nomatch Class="PatchOperationAdd">
      <xpath>*/StatDef[defName = "ButcheryFleshSpeed"]</xpath>
        <order>Prepend</order>
        <value>
          <parts>
            <li Class="Maux36.RimPsyche.Disposition.PsycheDeliberationWorkspeedStatPart"/>
          </parts>
        </value>
    </nomatch>
  </Operation>

  <Operation Class="PatchOperationConditional">
    <xpath>*/StatDef[defName = "ButcheryMechanoidSpeed"]/parts</xpath>
    <match Class="PatchOperationAdd">
      <xpath>*/StatDef[defName = "ButcheryMechanoidSpeed"]/parts</xpath>
        <order>Prepend</order>
        <value>
          <li Class="Maux36.RimPsyche.Disposition.PsycheDeliberationWorkspeedStatPart"/>
        </value>
    </match>
    <nomatch Class="PatchOperationAdd">
      <xpath>*/StatDef[defName = "ButcheryMechanoidSpeed"]</xpath>
        <order>Prepend</order>
        <value>
          <parts>
            <li Class="Maux36.RimPsyche.Disposition.PsycheDeliberationWorkspeedStatPart"/>
          </parts>
        </value>
    </nomatch>
  </Operation>


  <!-- Yield -->

  <Operation Class="PatchOperationConditional">
    <xpath>*/StatDef[defName = "MiningYield"]/parts</xpath>
    <match Class="PatchOperationAdd">
      <xpath>*/StatDef[defName = "MiningYield"]/parts</xpath>
        <order>Prepend</order>
        <value>
          <li Class="Maux36.RimPsyche.Disposition.PsycheDeliberationYieldChanceStatPart">
            <skill>Mining</skill>
          </li>
        </value>
    </match>
    <nomatch Class="PatchOperationAdd">
      <xpath>*/StatDef[defName = "MiningYield"]</xpath>
        <order>Prepend</order>
        <value>
          <parts>
            <li Class="Maux36.RimPsyche.Disposition.PsycheDeliberationYieldChanceStatPart">
            <skill>Mining</skill>
          </li>
          </parts>
        </value>
    </nomatch>
  </Operation>

  <Operation Class="PatchOperationConditional">
    <xpath>*/StatDef[defName = "AnimalGatherYield"]/parts</xpath>
    <match Class="PatchOperationAdd">
      <xpath>*/StatDef[defName = "AnimalGatherYield"]/parts</xpath>
        <order>Prepend</order>
        <value>
          <li Class="Maux36.RimPsyche.Disposition.PsycheDeliberationYieldChanceStatPart">
            <skill>Animals</skill>
          </li>
        </value>
    </match>
    <nomatch Class="PatchOperationAdd">
      <xpath>*/StatDef[defName = "AnimalGatherYield"]</xpath>
        <order>Prepend</order>
        <value>
          <parts>
            <li Class="Maux36.RimPsyche.Disposition.PsycheDeliberationYieldChanceStatPart">
            <skill>Animals</skill>
          </li>
          </parts>
        </value>
    </nomatch>
  </Operation>

  <Operation Class="PatchOperationConditional">
    <xpath>*/StatDef[defName = "PlantHarvestYield"]/parts</xpath>
    <match Class="PatchOperationAdd">
      <xpath>*/StatDef[defName = "PlantHarvestYield"]/parts</xpath>
        <order>Prepend</order>
        <value>
          <li Class="Maux36.RimPsyche.Disposition.PsycheDeliberationYieldChanceStatPart">
            <skill>Plants</skill>
          </li>
        </value>
    </match>
    <nomatch Class="PatchOperationAdd">
      <xpath>*/StatDef[defName = "PlantHarvestYield"]</xpath>
        <order>Prepend</order>
        <value>
          <parts>
            <li Class="Maux36.RimPsyche.Disposition.PsycheDeliberationYieldChanceStatPart">
            <skill>Plants</skill>
          </li>
          </parts>
        </value>
    </nomatch>
  </Operation>

  <Operation Class="PatchOperationConditional">
    <xpath>*/StatDef[defName = "ConstructSuccessChance"]/parts</xpath>
    <match Class="PatchOperationAdd">
      <xpath>*/StatDef[defName = "ConstructSuccessChance"]/parts</xpath>
        <order>Prepend</order>
        <value>
          <li Class="Maux36.RimPsyche.Disposition.PsycheDeliberationYieldChanceStatPart">
            <skill>Construction</skill>
          </li>
        </value>
    </match>
    <nomatch Class="PatchOperationAdd">
      <xpath>*/StatDef[defName = "ConstructSuccessChance"]</xpath>
        <order>Prepend</order>
        <value>
          <parts>
            <li Class="Maux36.RimPsyche.Disposition.PsycheDeliberationYieldChanceStatPart">
            <skill>Construction</skill>
          </li>
          </parts>
        </value>
    </nomatch>
  </Operation>

  <Operation Class="PatchOperationConditional">
    <xpath>*/StatDef[defName = "FixBrokenDownBuildingSuccessChance"]/parts</xpath>
    <match Class="PatchOperationAdd">
      <xpath>*/StatDef[defName = "FixBrokenDownBuildingSuccessChance"]/parts</xpath>
        <order>Prepend</order>
        <value>
          <li Class="Maux36.RimPsyche.Disposition.PsycheDeliberationYieldChanceStatPart">
            <skill>Construction</skill>
          </li>
        </value>
    </match>
    <nomatch Class="PatchOperationAdd">
      <xpath>*/StatDef[defName = "FixBrokenDownBuildingSuccessChance"]</xpath>
        <order>Prepend</order>
        <value>
          <parts>
            <li Class="Maux36.RimPsyche.Disposition.PsycheDeliberationYieldChanceStatPart">
            <skill>Construction</skill>
          </li>
          </parts>
        </value>
    </nomatch>
  </Operation>

  <Operation Class="PatchOperationConditional">
    <xpath>*/StatDef[defName = "MedicalTendQuality"]/parts</xpath>
    <match Class="PatchOperationAdd">
      <xpath>*/StatDef[defName = "MedicalTendQuality"]/parts</xpath>
        <order>Prepend</order>
        <value>
          <li Class="Maux36.RimPsyche.Disposition.PsycheDeliberationQualityStatPart"/>
        </value>
    </match>
    <nomatch Class="PatchOperationAdd">
      <xpath>*/StatDef[defName = "MedicalTendQuality"]</xpath>
        <order>Prepend</order>
        <value>
          <parts>
            <li Class="Maux36.RimPsyche.Disposition.PsycheDeliberationQualityStatPart"/>
          </parts>
        </value>
    </nomatch>
  </Operation>

  <Operation Class="PatchOperationConditional">
    <xpath>*/StatDef[defName = "MedicalSurgerySuccessChance"]/parts</xpath>
    <match Class="PatchOperationAdd">
      <xpath>*/StatDef[defName = "MedicalSurgerySuccessChance"]/parts</xpath>
        <order>Prepend</order>
        <value>
          <li Class="Maux36.RimPsyche.Disposition.PsycheDeliberationOperationChanceStatPart"/>
        </value>
    </match>
    <nomatch Class="PatchOperationAdd">
      <xpath>*/StatDef[defName = "MedicalSurgerySuccessChance"]</xpath>
        <order>Prepend</order>
        <value>
          <parts>
            <li Class="Maux36.RimPsyche.Disposition.PsycheDeliberationOperationChanceStatPart"/>
          </parts>
        </value>
    </nomatch>
  </Operation>
  
  <Operation Class="PatchOperationConditional">
    <xpath>*/StatDef[defName = "FoodPoisonChance"]/parts</xpath>
    <match Class="PatchOperationAdd">
      <xpath>*/StatDef[defName = "FoodPoisonChance"]/parts</xpath>
        <order>Prepend</order>
        <value>
          <li Class="Maux36.RimPsyche.Disposition.PsycheDeliberationFoodpoisonChanceStatpart"/>
        </value>
    </match>
    <nomatch Class="PatchOperationAdd">
      <xpath>*/StatDef[defName = "FoodPoisonChance"]</xpath>
        <order>Prepend</order>
        <value>
          <parts>
            <li Class="Maux36.RimPsyche.Disposition.PsycheDeliberationFoodpoisonChanceStatpart"/>
          </parts>
        </value>
    </nomatch>
  </Operation>
  
  <Operation Class="PatchOperationConditional">
    <xpath>*/StatDef[defName = "ButcheryFleshEfficiency"]/parts</xpath>
    <match Class="PatchOperationAdd">
      <xpath>*/StatDef[defName = "ButcheryFleshEfficiency"]/parts</xpath>
        <order>Prepend</order>
        <value>
          <li Class="Maux36.RimPsyche.Disposition.PsycheDeliberationButcherEfficiency"/>
        </value>
    </match>
    <nomatch Class="PatchOperationAdd">
      <xpath>*/StatDef[defName = "ButcheryFleshEfficiency"]</xpath>
        <order>Prepend</order>
        <value>
          <parts>
            <li Class="Maux36.RimPsyche.Disposition.PsycheDeliberationButcherEfficiency"/>
          </parts>
        </value>
    </nomatch>
  </Operation>
  
  <Operation Class="PatchOperationConditional">
    <xpath>*/StatDef[defName = "ButcheryMechanoidEfficiency"]/parts</xpath>
    <match Class="PatchOperationAdd">
      <xpath>*/StatDef[defName = "ButcheryMechanoidEfficiency"]/parts</xpath>
        <order>Prepend</order>
        <value>
          <li Class="Maux36.RimPsyche.Disposition.PsycheDeliberationButcherEfficiency"/>
        </value>
    </match>
    <nomatch Class="PatchOperationAdd">
      <xpath>*/StatDef[defName = "ButcheryMechanoidEfficiency"]</xpath>
        <order>Prepend</order>
        <value>
          <parts>
            <li Class="Maux36.RimPsyche.Disposition.PsycheDeliberationButcherEfficiency"/>
          </parts>
        </value>
    </nomatch>
  </Operation>

</Patch>
